pythonvideoannotator_module_importexport/__init__.py
pythonvideoannotator_module_importexport/export_window.py
pythonvideoannotator_module_importexport/module.py
pythonvideoannotator_module_importexport/models/__init__.py
pythonvideoannotator_module_importexport/models/video/__init__.py
pythonvideoannotator_module_importexport/models/video/objects/__init__.py
pythonvideoannotator_module_importexport/models/video/objects/image/__init__.py
pythonvideoannotator_module_importexport/models/video/objects/image/importexport_image.py
pythonvideoannotator_module_importexport/models/video/objects/object2d/__init__.py
pythonvideoannotator_module_importexport/models/video/objects/object2d/datasets/__init__.py
pythonvideoannotator_module_importexport/models/video/objects/object2d/datasets/path/__init__.py
pythonvideoannotator_module_importexport/models/video/objects/object2d/datasets/path/importexport_path.py
pythonvideoannotator_module_importexport/models/video/objects/object2d/datasets/value/__init__.py
pythonvideoannotator_module_importexport/models/video/objects/object2d/datasets/value/importexport_value.py
Python_video_annotator_module_import_export-0.5.23.dist-info/METADATA
Python_video_annotator_module_import_export-0.5.23.dist-info/WHEEL
Python_video_annotator_module_import_export-0.5.23.dist-info/top_level.txt
Python_video_annotator_module_import_export-0.5.23.dist-info/RECORD
